lrs/__init__.py
lrs/py.typed
lrs/benchmarks/__init__.py
lrs/benchmarks/chaos_scriptorium.py
lrs/benchmarks/gaia_benchmark.py
lrs/core/__init__.py
lrs/core/free_energy.py
lrs/core/lens.py
lrs/core/precision.py
lrs/core/registry.py
lrs/inference/__init__.py
lrs/inference/evaluator.py
lrs/inference/llm_policy_generator.py
lrs/inference/prompts.py
lrs/integration/__init__.py
lrs/integration/autogpt_adapter.py
lrs/integration/langchain_adapter.py
lrs/integration/langgraph.py
lrs/integration/openai_assistants.py
lrs/monitoring/__init__.py
lrs/monitoring/dashboard.py
lrs/monitoring/structured_logging.py
lrs/monitoring/tracker.py
lrs/multi_agent/__init__.py
lrs/multi_agent/communication.py
lrs/multi_agent/coordinator.py
lrs/multi_agent/multi_agent_free_energy.py
lrs/multi_agent/shared_state.py
lrs/multi_agent/social_precision.py
lrs_agents-0.2.1.dist-info/licenses/LICENSE
lrs_agents-0.2.1.dist-info/METADATA
lrs_agents-0.2.1.dist-info/WHEEL
lrs_agents-0.2.1.dist-info/top_level.txt
lrs_agents-0.2.1.dist-info/RECORD
