Metadata-Version: 2.4
Name: lrs-agents
Version: 0.2.1
Summary: Resilient AI agents via Active Inference
Author: LRS-Agents Contributors
License: MIT
Project-URL: Homepage, https://github.com/NeuralBlitz/lrs-agents
Project-URL: Documentation, https://lrs-agents.readthedocs.io
Project-URL: Repository, https://github.com/NeuralBlitz/lrs-agents
Project-URL: Issues, https://github.com/NeuralBlitz/lrs-agents/issues
Keywords: active-inference,ai-agents,langchain,llm,reinforcement-learning
Classifier: Development Status :: 4 - Beta
Classifier: Intended Audience :: Developers
Classifier: Intended Audience :: Science/Research
Classifier: License :: OSI Approved :: MIT License
Classifier: Programming Language :: Python :: 3
Classifier: Programming Language :: Python :: 3.9
Classifier: Programming Language :: Python :: 3.10
Classifier: Programming Language :: Python :: 3.11
Classifier: Programming Language :: Python :: 3.12
Classifier: Topic :: Scientific/Engineering :: Artificial Intelligence
Requires-Python: >=3.9
License-File: LICENSE
Requires-Dist: langchain>=0.1.0
Requires-Dist: langchain-anthropic>=0.1.0
Requires-Dist: langchain-openai>=0.0.5
Requires-Dist: langchain-community>=0.0.20
Requires-Dist: langgraph>=0.0.20
Requires-Dist: pydantic>=2.5.0
Requires-Dist: typing-extensions>=4.9.0
Requires-Dist: numpy>=1.24.0
Requires-Dist: scipy>=1.11.0
Provides-Extra: langchain
Requires-Dist: langchain>=0.1.0; extra == "langchain"
Requires-Dist: langchain-community>=0.0.20; extra == "langchain"
Provides-Extra: openai
Requires-Dist: openai>=1.0.0; extra == "openai"
Provides-Extra: monitoring
Requires-Dist: streamlit>=1.28.0; extra == "monitoring"
Requires-Dist: plotly>=5.18.0; extra == "monitoring"
Requires-Dist: matplotlib>=3.7.0; extra == "monitoring"
Provides-Extra: test
Requires-Dist: pytest>=7.4.0; extra == "test"
Requires-Dist: pytest-cov>=4.1.0; extra == "test"
Requires-Dist: pytest-asyncio>=0.21.0; extra == "test"
Requires-Dist: pytest-mock>=3.12.0; extra == "test"
Provides-Extra: dev
Requires-Dist: black>=23.0.0; extra == "dev"
Requires-Dist: ruff>=0.1.0; extra == "dev"
Requires-Dist: mypy>=1.7.0; extra == "dev"
Requires-Dist: pre-commit>=3.5.0; extra == "dev"
Provides-Extra: all
Requires-Dist: lrs-agents[dev,langchain,monitoring,openai,test]; extra == "all"
Dynamic: license-file
